happyreport/__init__.py
happyreport/cmd.py
happyreport/happy.py
happyreport/core/__init__.py
happyreport/core/clean.py
happyreport/core/verify.py
happyreport/email/__init__.py
happyreport/email/smtp.py
happyreport/format/__init__.py
happyreport/format/format.py
happyreport/template/__init__.py
happyreport/template/custom.py
happyreport/template/logger.py
happyreport/template/main.py
happyreport/template/settings.py
happyreport-0.0.11.dist-info/LICENSE
happyreport-0.0.11.dist-info/METADATA
happyreport-0.0.11.dist-info/WHEEL
happyreport-0.0.11.dist-info/entry_points.txt
happyreport-0.0.11.dist-info/top_level.txt
happyreport-0.0.11.dist-info/RECORD
