Metadata-Version: 2.1
Name: happyreport
Version: 0.0.11
Summary: Standardized report mail sending module
Home-page: UNKNOWN
Author: wuhaoyu
Author-email: wuhaoyu96@163.com
License: UNKNOWN
Platform: UNKNOWN
Classifier: Programming Language :: Python :: 3
Classifier: License :: OSI Approved :: MIT License
Classifier: Operating System :: OS Independent
Requires-Python: >=3.4
Requires-Dist: pandas
